[{"id":"60129","area":{"x":6,"y":3,"z":21},"centroid":{"x":1611,"y":4518,"z":2100},"post":{"x":1611,"y":4515,"z":2100},"pre":{"x":1613,"y":4523,"z":2102}},{"id":"60167","area":{"x":1,"y":0,"z":10},"centroid":{"x":1462,"y":4654,"z":2148},"post":{"x":1460,"y":4654,"z":2148},"pre":{"x":1464,"y":4656,"z":2149}},{"id":"60204","area":{"x":11,"y":0,"z":0},"centroid":{"x":1527,"y":4359,"z":2229},"post":{"x":1527,"y":4358,"z":2228},"pre":{"x":1527,"y":4361,"z":2230}},{"id":"60204","area":{"x":0,"y":0,"z":3},"centroid":{"x":1549,"y":4135,"z":2210},"post":{"x":1549,"y":4135,"z":2210},"pre":{"x":1550,"y":4136,"z":2210}},{"id":"60208","area":{"x":3,"y":4,"z":91},"centroid":{"x":1601,"y":4018,"z":2436},"post":{"x":1596,"y":4011,"z":2435},"pre":{"x":1608,"y":4024,"z":2437}},{"id":"60208","area":{"x":4,"y":1,"z":5},"centroid":{"x":1612,"y":4006,"z":2434},"post":{"x":1610,"y":4004,"z":2434},"pre":{"x":1613,"y":4009,"z":2435}},{"id":"60209","area":{"x":14,"y":1,"z":7},"centroid":{"x":1459,"y":4612,"z":2164},"post":{"x":1458,"y":4611,"z":2162},"pre":{"x":1460,"y":4615,"z":2167}},{"id":"60208","area":{"x":36,"y":4,"z":4},"centroid":{"x":1620,"y":3973,"z":2421},"post":{"x":1620,"y":3970,"z":2417},"pre":{"x":1622,"y":3977,"z":2425}},{"id":"60208","area":{"x":17,"y":6,"z":34},"centroid":{"x":1625,"y":4016,"z":2468},"post":{"x":1622,"y":4013,"z":2466},"pre":{"x":1628,"y":4020,"z":2471}},{"id":"60209","area":{"x":9,"y":6,"z":27},"centroid":{"x":1477,"y":4586,"z":2164},"post":{"x":1474,"y":4584,"z":2163},"pre":{"x":1480,"y":4590,"z":2166}},{"id":"60210","area":{"x":13,"y":43,"z":8},"centroid":{"x":1570,"y":4358,"z":1996},"post":{"x":1565,"y":4356,"z":1993},"pre":{"x":1573,"y":4361,"z":2001}},{"id":"60454","area":{"x":4,"y":55,"z":4},"centroid":{"x":1622,"y":4013,"z":2465},"post":{"x":1619,"y":4013,"z":2461},"pre":{"x":1627,"y":4015,"z":2469}},{"id":"60600","area":{"x":10,"y":18,"z":22},"centroid":{"x":1571,"y":4619,"z":2455},"post":{"x":1569,"y":4615,"z":2454},"pre":{"x":1574,"y":4623,"z":2458}},{"id":"60164","area":{"x":20,"y":126,"z":70},"centroid":{"x":1399,"y":4224,"z":2341},"post":{"x":1392,"y":4222,"z":2336},"pre":{"x":1407,"y":4229,"z":2349}},{"id":"60170","area":{"x":57,"y":5,"z":3},"centroid":{"x":1584,"y":3903,"z":2415},"post":{"x":1583,"y":3896,"z":2411},"pre":{"x":1585,"y":3910,"z":2418}},{"id":"60170","area":{"x":2,"y":4,"z":12},"centroid":{"x":1587,"y":4012,"z":2417},"post":{"x":1586,"y":4011,"z":2417},"pre":{"x":1591,"y":4014,"z":2418}},{"id":"70023","area":{"x":2,"y":28,"z":25},"centroid":{"x":1424,"y":4706,"z":2125},"post":{"x":1421,"y":4703,"z":2121},"pre":{"x":1430,"y":4713,"z":2130}},{"id":"70024","area":{"x":36,"y":28,"z":17},"centroid":{"x":1424,"y":4241,"z":2365},"post":{"x":1422,"y":4236,"z":2361},"pre":{"x":1428,"y":4245,"z":2372}},{"id":"70024","area":{"x":1,"y":4,"z":3},"centroid":{"x":1429,"y":4252,"z":2379},"post":{"x":1428,"y":4252,"z":2379},"pre":{"x":1431,"y":4253,"z":2380}},{"id":"70024","area":{"x":3,"y":0,"z":3},"centroid":{"x":1430,"y":4703,"z":2130},"post":{"x":1430,"y":4702,"z":2130},"pre":{"x":1431,"y":4704,"z":2131}},{"id":"70025","area":{"x":74,"y":19,"z":26},"centroid":{"x":1414,"y":4686,"z":2129},"post":{"x":1406,"y":4668,"z":2119},"pre":{"x":1422,"y":4700,"z":2136}},{"id":"70025","area":{"x":3,"y":0,"z":6},"centroid":{"x":1422,"y":4660,"z":2140},"post":{"x":1422,"y":4658,"z":2139},"pre":{"x":1423,"y":4662,"z":2141}},{"id":"70023","area":{"x":63,"y":14,"z":108},"centroid":{"x":1557,"y":3851,"z":2413},"post":{"x":1553,"y":3836,"z":2406},"pre":{"x":1565,"y":3867,"z":2419}},{"id":"70037","area":{"x":2,"y":1,"z":0},"centroid":{"x":1615,"y":4015,"z":2432},"post":{"x":1615,"y":4014,"z":2432},"pre":{"x":1615,"y":4016,"z":2432}},{"id":"70037","area":{"x":44,"y":23,"z":34},"centroid":{"x":1619,"y":4030,"z":2459},"post":{"x":1616,"y":4025,"z":2455},"pre":{"x":1622,"y":4036,"z":2463}},{"id":"70033","area":{"x":45,"y":31,"z":13},"centroid":{"x":1434,"y":4275,"z":2389},"post":{"x":1432,"y":4271,"z":2385},"pre":{"x":1439,"y":4279,"z":2394}},{"id":"70033","area":{"x":1,"y":5,"z":0},"centroid":{"x":1446,"y":4281,"z":2386},"post":{"x":1445,"y":4281,"z":2385},"pre":{"x":1447,"y":4282,"z":2387}},{"id":"60167","area":{"x":11,"y":21,"z":38},"centroid":{"x":1473,"y":4630,"z":2275},"post":{"x":1471,"y":4623,"z":2272},"pre":{"x":1475,"y":4634,"z":2280}},{"id":"60163","area":{"x":70,"y":44,"z":69},"centroid":{"x":1426,"y":4290,"z":2429},"post":{"x":1423,"y":4281,"z":2425},"pre":{"x":1431,"y":4299,"z":2436}},{"id":"60163","area":{"x":5,"y":0,"z":12},"centroid":{"x":1447,"y":4154,"z":2405},"post":{"x":1445,"y":4152,"z":2404},"pre":{"x":1449,"y":4156,"z":2406}},{"id":"60204","area":{"x":14,"y":20,"z":1},"centroid":{"x":1553,"y":4375,"z":2266},"post":{"x":1552,"y":4373,"z":2264},"pre":{"x":1556,"y":4377,"z":2269}},{"id":"60204","area":{"x":35,"y":57,"z":33},"centroid":{"x":1559,"y":4210,"z":2332},"post":{"x":1554,"y":4206,"z":2325},"pre":{"x":1566,"y":4214,"z":2339}},{"id":"60204","area":{"x":0,"y":0,"z":5},"centroid":{"x":1568,"y":4231,"z":2222},"post":{"x":1567,"y":4231,"z":2222},"pre":{"x":1569,"y":4232,"z":2222}},{"id":"60204","area":{"x":3,"y":9,"z":32},"centroid":{"x":1591,"y":4369,"z":2268},"post":{"x":1590,"y":4364,"z":2267},"pre":{"x":1594,"y":4373,"z":2269}},{"id":"60204","area":{"x":7,"y":6,"z":2},"centroid":{"x":1599,"y":4386,"z":2049},"post":{"x":1599,"y":4385,"z":2046},"pre":{"x":1601,"y":4388,"z":2053}},{"id":"60204","area":{"x":11,"y":12,"z":1},"centroid":{"x":1632,"y":4123,"z":2135},"post":{"x":1631,"y":4121,"z":2133},"pre":{"x":1635,"y":4125,"z":2137}},{"id":"70079","area":{"x":2,"y":7,"z":6},"centroid":{"x":1439,"y":4294,"z":2397},"post":{"x":1438,"y":4293,"z":2396},"pre":{"x":1441,"y":4297,"z":2399}},{"id":"70079","area":{"x":9,"y":1,"z":1},"centroid":{"x":1463,"y":4317,"z":2361},"post":{"x":1463,"y":4315,"z":2361},"pre":{"x":1464,"y":4320,"z":2363}},{"id":"70076","area":{"x":31,"y":17,"z":70},"centroid":{"x":1422,"y":4301,"z":2405},"post":{"x":1419,"y":4293,"z":2402},"pre":{"x":1426,"y":4314,"z":2410}},{"id":"70076","area":{"x":29,"y":25,"z":21},"centroid":{"x":1433,"y":4280,"z":2404},"post":{"x":1430,"y":4275,"z":2401},"pre":{"x":1437,"y":4284,"z":2408}},{"id":"60209","area":{"x":62,"y":33,"z":58},"centroid":{"x":1484,"y":4201,"z":2389},"post":{"x":1482,"y":4193,"z":2384},"pre":{"x":1488,"y":4209,"z":2397}},{"id":"70016","area":{"x":29,"y":102,"z":80},"centroid":{"x":1414,"y":4229,"z":2362},"post":{"x":1408,"y":4221,"z":2353},"pre":{"x":1418,"y":4238,"z":2371}},{"id":"60167","area":{"x":16,"y":25,"z":103},"centroid":{"x":1482,"y":4691,"z":2302},"post":{"x":1477,"y":4685,"z":2300},"pre":{"x":1487,"y":4700,"z":2303}},{"id":"70109","area":{"x":25,"y":17,"z":14},"centroid":{"x":1421,"y":4235,"z":2366},"post":{"x":1419,"y":4232,"z":2362},"pre":{"x":1423,"y":4238,"z":2370}},{"id":"60163","area":{"x":44,"y":9,"z":15},"centroid":{"x":1491,"y":4122,"z":2394},"post":{"x":1489,"y":4118,"z":2392},"pre":{"x":1493,"y":4126,"z":2399}},{"id":"70121","area":{"x":27,"y":10,"z":17},"centroid":{"x":1435,"y":4274,"z":2397},"post":{"x":1433,"y":4271,"z":2394},"pre":{"x":1439,"y":4277,"z":2401}},{"id":"70124","area":{"x":32,"y":1,"z":2},"centroid":{"x":1475,"y":4244,"z":2366},"post":{"x":1474,"y":4241,"z":2363},"pre":{"x":1476,"y":4247,"z":2370}},{"id":"70109","area":{"x":69,"y":17,"z":68},"centroid":{"x":1424,"y":4253,"z":2376},"post":{"x":1421,"y":4246,"z":2373},"pre":{"x":1428,"y":4262,"z":2381}},{"id":"70133","area":{"x":18,"y":16,"z":8},"centroid":{"x":1432,"y":4679,"z":2129},"post":{"x":1430,"y":4676,"z":2127},"pre":{"x":1435,"y":4683,"z":2132}},{"id":"70130","area":{"x":54,"y":19,"z":62},"centroid":{"x":1421,"y":4246,"z":2369},"post":{"x":1418,"y":4238,"z":2367},"pre":{"x":1424,"y":4256,"z":2372}},{"id":"70154","area":{"x":7,"y":5,"z":1},"centroid":{"x":1412,"y":4223,"z":2352},"post":{"x":1412,"y":4222,"z":2352},"pre":{"x":1414,"y":4225,"z":2354}},{"id":"70020","area":{"x":156,"y":133,"z":60},"centroid":{"x":1595,"y":4222,"z":2332},"post":{"x":1589,"y":4215,"z":2325},"pre":{"x":1605,"y":4232,"z":2341}},{"id":"70084","area":{"x":93,"y":115,"z":235},"centroid":{"x":1518,"y":4436,"z":2360},"post":{"x":1509,"y":4424,"z":2356},"pre":{"x":1527,"y":4444,"z":2367}},{"id":"70159","area":{"x":46,"y":3,"z":2},"centroid":{"x":1527,"y":4468,"z":2256},"post":{"x":1527,"y":4465,"z":2253},"pre":{"x":1528,"y":4472,"z":2260}},{"id":"60167","area":{"x":4,"y":18,"z":52},"centroid":{"x":1516,"y":4455,"z":2363},"post":{"x":1509,"y":4452,"z":2362},"pre":{"x":1521,"y":4461,"z":2366}},{"id":"70159","area":{"x":24,"y":8,"z":5},"centroid":{"x":1541,"y":4508,"z":2294},"post":{"x":1539,"y":4506,"z":2292},"pre":{"x":1542,"y":4511,"z":2298}},{"id":"70159","area":{"x":1,"y":0,"z":0},"centroid":{"x":1559,"y":4400,"z":2260},"post":{"x":1559,"y":4400,"z":2260},"pre":{"x":1559,"y":4400,"z":2260}},{"id":"70153","area":{"x":138,"y":34,"z":47},"centroid":{"x":1467,"y":4688,"z":2288},"post":{"x":1466,"y":4680,"z":2282},"pre":{"x":1472,"y":4696,"z":2296}},{"id":"60167","area":{"x":41,"y":36,"z":37},"centroid":{"x":1573,"y":4507,"z":2350},"post":{"x":1566,"y":4503,"z":2346},"pre":{"x":1577,"y":4515,"z":2353}},{"id":"70128","area":{"x":105,"y":40,"z":48},"centroid":{"x":1439,"y":4620,"z":2139},"post":{"x":1437,"y":4615,"z":2131},"pre":{"x":1443,"y":4624,"z":2149}},{"id":"60167","area":{"x":10,"y":49,"z":46},"centroid":{"x":1570,"y":4610,"z":2339},"post":{"x":1567,"y":4604,"z":2334},"pre":{"x":1575,"y":4616,"z":2346}},{"id":"60167","area":{"x":17,"y":11,"z":9},"centroid":{"x":1571,"y":4493,"z":2371},"post":{"x":1569,"y":4492,"z":2369},"pre":{"x":1573,"y":4496,"z":2374}},{"id":"70090","area":{"x":27,"y":44,"z":20},"centroid":{"x":1466,"y":4170,"z":2400},"post":{"x":1463,"y":4167,"z":2397},"pre":{"x":1471,"y":4176,"z":2404}},{"id":"70033","area":{"x":60,"y":3,"z":23},"centroid":{"x":1464,"y":4584,"z":2221},"post":{"x":1462,"y":4579,"z":2218},"pre":{"x":1466,"y":4592,"z":2224}},{"id":"70066","area":{"x":21,"y":32,"z":73},"centroid":{"x":1432,"y":4307,"z":2403},"post":{"x":1428,"y":4299,"z":2400},"pre":{"x":1440,"y":4312,"z":2406}},{"id":"70066","area":{"x":57,"y":15,"z":19},"centroid":{"x":1444,"y":4284,"z":2395},"post":{"x":1442,"y":4277,"z":2391},"pre":{"x":1447,"y":4292,"z":2398}},{"id":"70047","area":{"x":77,"y":65,"z":194},"centroid":{"x":1558,"y":4229,"z":2191},"post":{"x":1552,"y":4218,"z":2185},"pre":{"x":1563,"y":4245,"z":2200}},{"id":"70066","area":{"x":28,"y":52,"z":75},"centroid":{"x":1457,"y":4173,"z":2397},"post":{"x":1447,"y":4169,"z":2393},"pre":{"x":1464,"y":4179,"z":2403}},{"id":"70129","area":{"x":32,"y":20,"z":8},"centroid":{"x":1449,"y":4167,"z":2401},"post":{"x":1448,"y":4158,"z":2398},"pre":{"x":1452,"y":4172,"z":2404}},{"id":"70019","area":{"x":105,"y":59,"z":170},"centroid":{"x":1547,"y":4217,"z":2139},"post":{"x":1542,"y":4201,"z":2136},"pre":{"x":1553,"y":4238,"z":2147}},{"id":"70096","area":{"x":20,"y":21,"z":83},"centroid":{"x":1483,"y":4216,"z":2377},"post":{"x":1481,"y":4206,"z":2372},"pre":{"x":1487,"y":4228,"z":2381}},{"id":"70096","area":{"x":21,"y":2,"z":5},"centroid":{"x":1503,"y":4314,"z":2239},"post":{"x":1502,"y":4310,"z":2236},"pre":{"x":1504,"y":4318,"z":2242}},{"id":"70159","area":{"x":71,"y":111,"z":153},"centroid":{"x":1602,"y":4230,"z":2156},"post":{"x":1588,"y":4216,"z":2150},"pre":{"x":1611,"y":4242,"z":2166}},{"id":"70156","area":{"x":186,"y":102,"z":106},"centroid":{"x":1427,"y":4287,"z":2409},"post":{"x":1420,"y":4276,"z":2395},"pre":{"x":1440,"y":4296,"z":2426}},{"id":"70156","area":{"x":0,"y":0,"z":4},"centroid":{"x":1425,"y":4290,"z":2437},"post":{"x":1425,"y":4290,"z":2437},"pre":{"x":1426,"y":4291,"z":2437}},{"id":"70033","area":{"x":174,"y":94,"z":185},"centroid":{"x":1470,"y":4673,"z":2288},"post":{"x":1466,"y":4656,"z":2282},"pre":{"x":1475,"y":4688,"z":2300}},{"id":"70019","area":{"x":125,"y":144,"z":206},"centroid":{"x":1565,"y":3870,"z":2414},"post":{"x":1550,"y":3862,"z":2410},"pre":{"x":1576,"y":3880,"z":2420}},{"id":"60209","area":{"x":318,"y":85,"z":151},"centroid":{"x":1510,"y":4443,"z":2219},"post":{"x":1506,"y":4420,"z":2210},"pre":{"x":1516,"y":4462,"z":2233}},{"id":"60209","area":{"x":23,"y":44,"z":11},"centroid":{"x":1513,"y":4265,"z":2214},"post":{"x":1510,"y":4262,"z":2211},"pre":{"x":1518,"y":4270,"z":2219}},{"id":"60209","area":{"x":23,"y":26,"z":7},"centroid":{"x":1537,"y":4152,"z":2174},"post":{"x":1534,"y":4150,"z":2172},"pre":{"x":1540,"y":4156,"z":2177}},{"id":"70019","area":{"x":59,"y":17,"z":14},"centroid":{"x":1565,"y":4351,"z":2342},"post":{"x":1564,"y":4346,"z":2338},"pre":{"x":1567,"y":4362,"z":2347}},{"id":"70019","area":{"x":39,"y":25,"z":86},"centroid":{"x":1575,"y":3907,"z":2419},"post":{"x":1571,"y":3901,"z":2412},"pre":{"x":1582,"y":3914,"z":2423}},{"id":"70019","area":{"x":50,"y":39,"z":27},"centroid":{"x":1591,"y":3922,"z":2424},"post":{"x":1585,"y":3919,"z":2420},"pre":{"x":1594,"y":3930,"z":2428}},{"id":"70156","area":{"x":209,"y":56,"z":170},"centroid":{"x":1469,"y":4313,"z":2355},"post":{"x":1464,"y":4281,"z":2351},"pre":{"x":1477,"y":4350,"z":2365}},{"id":"60459","area":{"x":195,"y":291,"z":528},"centroid":{"x":1592,"y":4494,"z":2127},"post":{"x":1570,"y":4470,"z":2107},"pre":{"x":1632,"y":4512,"z":2142}},{"id":"70153","area":{"x":171,"y":76,"z":486},"centroid":{"x":1486,"y":4349,"z":2364},"post":{"x":1473,"y":4330,"z":2353},"pre":{"x":1499,"y":4375,"z":2368}},{"id":"70153","area":{"x":11,"y":8,"z":4},"centroid":{"x":1475,"y":4697,"z":2298},"post":{"x":1474,"y":4696,"z":2297},"pre":{"x":1477,"y":4700,"z":2301}},{"id":"70153","area":{"x":13,"y":26,"z":36},"centroid":{"x":1522,"y":4160,"z":2442},"post":{"x":1520,"y":4152,"z":2439},"pre":{"x":1525,"y":4166,"z":2446}},{"id":"60209","area":{"x":40,"y":145,"z":163},"centroid":{"x":1553,"y":4462,"z":2170},"post":{"x":1543,"y":4456,"z":2165},"pre":{"x":1565,"y":4473,"z":2179}},{"id":"60209","area":{"x":13,"y":3,"z":17},"centroid":{"x":1547,"y":4136,"z":2207},"post":{"x":1546,"y":4133,"z":2206},"pre":{"x":1549,"y":4139,"z":2209}},{"id":"60209","area":{"x":15,"y":13,"z":36},"centroid":{"x":1560,"y":4412,"z":2191},"post":{"x":1555,"y":4410,"z":2190},"pre":{"x":1564,"y":4416,"z":2193}},{"id":"70153","area":{"x":143,"y":15,"z":109},"centroid":{"x":1585,"y":4311,"z":2325},"post":{"x":1581,"y":4294,"z":2322},"pre":{"x":1589,"y":4324,"z":2331}},{"id":"70153","area":{"x":10,"y":50,"z":21},"centroid":{"x":1598,"y":4366,"z":2288},"post":{"x":1595,"y":4364,"z":2283},"pre":{"x":1602,"y":4370,"z":2294}},{"id":"70153","area":{"x":1,"y":2,"z":0},"centroid":{"x":1600,"y":4395,"z":2127},"post":{"x":1600,"y":4395,"z":2127},"pre":{"x":1601,"y":4396,"z":2127}},{"id":"70153","area":{"x":37,"y":16,"z":10},"centroid":{"x":1602,"y":4391,"z":2167},"post":{"x":1601,"y":4389,"z":2164},"pre":{"x":1606,"y":4394,"z":2172}},{"id":"70153","area":{"x":0,"y":1,"z":1},"centroid":{"x":1607,"y":4393,"z":2123},"post":{"x":1607,"y":4393,"z":2123},"pre":{"x":1607,"y":4394,"z":2124}},{"id":"60209","area":{"x":60,"y":160,"z":107},"centroid":{"x":1575,"y":4246,"z":2186},"post":{"x":1558,"y":4240,"z":2180},"pre":{"x":1590,"y":4250,"z":2191}},{"id":"60209","area":{"x":4,"y":0,"z":6},"centroid":{"x":1578,"y":4236,"z":2218},"post":{"x":1578,"y":4235,"z":2218},"pre":{"x":1579,"y":4239,"z":2219}},{"id":"60209","area":{"x":39,"y":22,"z":170},"centroid":{"x":1590,"y":4219,"z":2340},"post":{"x":1583,"y":4208,"z":2337},"pre":{"x":1601,"y":4231,"z":2347}},{"id":"60459","area":{"x":133,"y":532,"z":615},"centroid":{"x":1843,"y":4444,"z":2165},"post":{"x":1760,"y":4431,"z":2138},"pre":{"x":1926,"y":4453,"z":2186}},{"id":"60209","area":{"x":11,"y":23,"z":20},"centroid":{"x":1593,"y":4479,"z":2127},"post":{"x":1589,"y":4476,"z":2126},"pre":{"x":1598,"y":4483,"z":2131}},{"id":"60209","area":{"x":96,"y":56,"z":53},"centroid":{"x":1601,"y":4240,"z":2168},"post":{"x":1594,"y":4232,"z":2157},"pre":{"x":1609,"y":4247,"z":2177}},{"id":"60209","area":{"x":13,"y":11,"z":10},"centroid":{"x":1602,"y":4392,"z":2161},"post":{"x":1600,"y":4390,"z":2159},"pre":{"x":1604,"y":4395,"z":2164}},{"id":"60209","area":{"x":16,"y":1,"z":5},"centroid":{"x":1606,"y":4417,"z":2267},"post":{"x":1606,"y":4414,"z":2266},"pre":{"x":1607,"y":4420,"z":2269}},{"id":"60209","area":{"x":1,"y":28,"z":6},"centroid":{"x":1615,"y":4195,"z":2322},"post":{"x":1611,"y":4195,"z":2320},"pre":{"x":1619,"y":4196,"z":2324}},{"id":"60209","area":{"x":78,"y":33,"z":37},"centroid":{"x":1632,"y":4129,"z":2136},"post":{"x":1629,"y":4122,"z":2131},"pre":{"x":1636,"y":4136,"z":2141}},{"id":"60209","area":{"x":9,"y":19,"z":45},"centroid":{"x":1687,"y":4472,"z":2084},"post":{"x":1683,"y":4469,"z":2083},"pre":{"x":1692,"y":4475,"z":2086}},{"id":"60209","area":{"x":34,"y":46,"z":176},"centroid":{"x":1825,"y":4442,"z":2165},"post":{"x":1806,"y":4437,"z":2160},"pre":{"x":1848,"y":4446,"z":2171}},{"id":"60209","area":{"x":0,"y":0,"z":2},"centroid":{"x":1856,"y":4444,"z":2175},"post":{"x":1856,"y":4444,"z":2175},"pre":{"x":1857,"y":4444,"z":2175}},{"id":"60209","area":{"x":2,"y":0,"z":20},"centroid":{"x":1868,"y":4442,"z":2177},"post":{"x":1864,"y":4441,"z":2177},"pre":{"x":1872,"y":4443,"z":2178}},{"id":"60209","area":{"x":17,"y":12,"z":105},"centroid":{"x":1904,"y":4426,"z":2186},"post":{"x":1898,"y":4417,"z":2186},"pre":{"x":1913,"y":4435,"z":2188}},{"id":"60209","area":{"x":7,"y":3,"z":55},"centroid":{"x":1923,"y":4427,"z":2183},"post":{"x":1917,"y":4424,"z":2182},"pre":{"x":1928,"y":4430,"z":2186}}]
