[{"id":"60180","area":{"x":0,"y":12,"z":0},"centroid":{"x":1273,"y":5097,"z":1219},"post":{"x":1272,"y":5097,"z":1218},"pre":{"x":1276,"y":5097,"z":1221}},{"id":"60176","area":{"x":1,"y":39,"z":2},"centroid":{"x":1254,"y":5056,"z":1146},"post":{"x":1251,"y":5056,"z":1144},"pre":{"x":1258,"y":5057,"z":1149}},{"id":"60180","area":{"x":28,"y":3,"z":32},"centroid":{"x":1411,"y":5171,"z":1261},"post":{"x":1408,"y":5166,"z":1260},"pre":{"x":1414,"y":5176,"z":1264}},{"id":"60181","area":{"x":0,"y":3,"z":15},"centroid":{"x":1337,"y":4816,"z":1510},"post":{"x":1336,"y":4815,"z":1510},"pre":{"x":1339,"y":4818,"z":1511}},{"id":"60174","area":{"x":26,"y":48,"z":42},"centroid":{"x":1268,"y":4978,"z":1425},"post":{"x":1264,"y":4970,"z":1422},"pre":{"x":1276,"y":4983,"z":1431}},{"id":"60176","area":{"x":42,"y":18,"z":38},"centroid":{"x":1303,"y":5050,"z":1124},"post":{"x":1301,"y":5041,"z":1119},"pre":{"x":1305,"y":5059,"z":1129}},{"id":"60176","area":{"x":48,"y":8,"z":14},"centroid":{"x":1307,"y":4970,"z":1262},"post":{"x":1305,"y":4964,"z":1260},"pre":{"x":1309,"y":4976,"z":1265}},{"id":"60176","area":{"x":2,"y":4,"z":4},"centroid":{"x":1318,"y":5017,"z":1149},"post":{"x":1317,"y":5017,"z":1149},"pre":{"x":1319,"y":5019,"z":1150}},{"id":"60198","area":{"x":13,"y":30,"z":28},"centroid":{"x":1302,"y":5040,"z":1468},"post":{"x":1299,"y":5035,"z":1466},"pre":{"x":1306,"y":5043,"z":1471}},{"id":"70014","area":{"x":2,"y":3,"z":51},"centroid":{"x":1425,"y":5141,"z":1322},"post":{"x":1421,"y":5133,"z":1321},"pre":{"x":1432,"y":5150,"z":1324}},{"id":"70016","area":{"x":14,"y":25,"z":10},"centroid":{"x":1327,"y":5149,"z":1398},"post":{"x":1322,"y":5148,"z":1392},"pre":{"x":1331,"y":5152,"z":1404}},{"id":"70025","area":{"x":0,"y":2,"z":22},"centroid":{"x":1359,"y":5146,"z":1316},"post":{"x":1357,"y":5141,"z":1316},"pre":{"x":1362,"y":5151,"z":1317}},{"id":"70027","area":{"x":3,"y":16,"z":3},"centroid":{"x":1356,"y":5439,"z":1323},"post":{"x":1354,"y":5437,"z":1320},"pre":{"x":1359,"y":5441,"z":1329}},{"id":"70033","area":{"x":20,"y":15,"z":10},"centroid":{"x":1392,"y":5433,"z":1315},"post":{"x":1389,"y":5429,"z":1314},"pre":{"x":1396,"y":5437,"z":1318}},{"id":"70035","area":{"x":2,"y":1,"z":23},"centroid":{"x":1390,"y":5437,"z":1313},"post":{"x":1386,"y":5436,"z":1313},"pre":{"x":1394,"y":5439,"z":1314}},{"id":"70071","area":{"x":60,"y":7,"z":12},"centroid":{"x":1260,"y":4994,"z":1408},"post":{"x":1259,"y":4988,"z":1405},"pre":{"x":1263,"y":4999,"z":1413}},{"id":"70068","area":{"x":36,"y":12,"z":48},"centroid":{"x":1375,"y":5012,"z":1391},"post":{"x":1373,"y":5001,"z":1384},"pre":{"x":1377,"y":5024,"z":1396}},{"id":"70079","area":{"x":19,"y":27,"z":16},"centroid":{"x":1403,"y":5205,"z":1270},"post":{"x":1400,"y":5204,"z":1268},"pre":{"x":1408,"y":5208,"z":1273}},{"id":"70079","area":{"x":18,"y":8,"z":6},"centroid":{"x":1409,"y":5171,"z":1264},"post":{"x":1407,"y":5166,"z":1263},"pre":{"x":1412,"y":5176,"z":1267}},{"id":"70087","area":{"x":3,"y":0,"z":4},"centroid":{"x":1341,"y":5388,"z":1326},"post":{"x":1341,"y":5387,"z":1326},"pre":{"x":1342,"y":5389,"z":1327}},{"id":"70087","area":{"x":14,"y":7,"z":2},"centroid":{"x":1350,"y":5399,"z":1321},"post":{"x":1348,"y":5397,"z":1319},"pre":{"x":1353,"y":5403,"z":1323}},{"id":"70087","area":{"x":21,"y":18,"z":16},"centroid":{"x":1409,"y":4930,"z":1441},"post":{"x":1408,"y":4925,"z":1437},"pre":{"x":1412,"y":4934,"z":1447}},{"id":"70024","area":{"x":18,"y":57,"z":79},"centroid":{"x":1401,"y":5166,"z":1310},"post":{"x":1395,"y":5159,"z":1305},"pre":{"x":1407,"y":5178,"z":1315}},{"id":"70124","area":{"x":34,"y":17,"z":12},"centroid":{"x":1384,"y":5002,"z":1405},"post":{"x":1383,"y":5000,"z":1401},"pre":{"x":1386,"y":5005,"z":1411}},{"id":"70124","area":{"x":2,"y":5,"z":10},"centroid":{"x":1392,"y":5437,"z":1317},"post":{"x":1390,"y":5435,"z":1315},"pre":{"x":1394,"y":5440,"z":1319}},{"id":"70110","area":{"x":13,"y":31,"z":56},"centroid":{"x":1351,"y":5289,"z":1293},"post":{"x":1350,"y":5281,"z":1287},"pre":{"x":1355,"y":5303,"z":1301}},{"id":"70110","area":{"x":33,"y":6,"z":8},"centroid":{"x":1354,"y":5312,"z":1308},"post":{"x":1354,"y":5308,"z":1305},"pre":{"x":1356,"y":5317,"z":1311}},{"id":"70110","area":{"x":16,"y":9,"z":20},"centroid":{"x":1372,"y":5017,"z":1389},"post":{"x":1371,"y":5013,"z":1387},"pre":{"x":1374,"y":5021,"z":1391}},{"id":"70126","area":{"x":35,"y":17,"z":81},"centroid":{"x":1404,"y":4931,"z":1437},"post":{"x":1401,"y":4923,"z":1433},"pre":{"x":1409,"y":4939,"z":1444}},{"id":"70126","area":{"x":14,"y":3,"z":7},"centroid":{"x":1406,"y":4950,"z":1444},"post":{"x":1406,"y":4948,"z":1442},"pre":{"x":1408,"y":4953,"z":1446}},{"id":"70144","area":{"x":88,"y":24,"z":22},"centroid":{"x":1360,"y":5262,"z":1293},"post":{"x":1357,"y":5253,"z":1286},"pre":{"x":1364,"y":5272,"z":1301}},{"id":"70146","area":{"x":0,"y":3,"z":1},"centroid":{"x":1417,"y":4900,"z":1451},"post":{"x":1416,"y":4900,"z":1451},"pre":{"x":1418,"y":4901,"z":1452}},{"id":"70150","area":{"x":11,"y":17,"z":19},"centroid":{"x":1406,"y":4962,"z":1437},"post":{"x":1404,"y":4959,"z":1436},"pre":{"x":1409,"y":4967,"z":1442}},{"id":"70156","area":{"x":1,"y":8,"z":25},"centroid":{"x":1350,"y":5018,"z":1385},"post":{"x":1348,"y":5017,"z":1385},"pre":{"x":1354,"y":5022,"z":1387}},{"id":"70156","area":{"x":1,"y":4,"z":6},"centroid":{"x":1366,"y":5033,"z":1380},"post":{"x":1366,"y":5032,"z":1380},"pre":{"x":1367,"y":5035,"z":1382}},{"id":"70034","area":{"x":99,"y":46,"z":109},"centroid":{"x":1401,"y":4952,"z":1430},"post":{"x":1397,"y":4930,"z":1425},"pre":{"x":1408,"y":4967,"z":1435}},{"id":"70131","area":{"x":0,"y":13,"z":17},"centroid":{"x":1295,"y":5064,"z":1156},"post":{"x":1291,"y":5061,"z":1156},"pre":{"x":1301,"y":5067,"z":1158}},{"id":"70034","area":{"x":3,"y":6,"z":29},"centroid":{"x":1410,"y":4920,"z":1438},"post":{"x":1407,"y":4915,"z":1437},"pre":{"x":1414,"y":4924,"z":1442}},{"id":"70131","area":{"x":3,"y":1,"z":2},"centroid":{"x":1301,"y":5077,"z":1166},"post":{"x":1301,"y":5077,"z":1166},"pre":{"x":1302,"y":5079,"z":1167}},{"id":"70094","area":{"x":71,"y":59,"z":81},"centroid":{"x":1374,"y":5428,"z":1312},"post":{"x":1366,"y":5423,"z":1305},"pre":{"x":1381,"y":5435,"z":1320}},{"id":"70131","area":{"x":33,"y":15,"z":12},"centroid":{"x":1313,"y":5023,"z":1146},"post":{"x":1310,"y":5018,"z":1144},"pre":{"x":1316,"y":5028,"z":1149}},{"id":"60174","area":{"x":142,"y":44,"z":35},"centroid":{"x":1279,"y":4984,"z":1409},"post":{"x":1276,"y":4968,"z":1402},"pre":{"x":1286,"y":4997,"z":1419}},{"id":"60174","area":{"x":0,"y":0,"z":6},"centroid":{"x":1278,"y":5179,"z":1424},"post":{"x":1278,"y":5178,"z":1424},"pre":{"x":1279,"y":5180,"z":1424}},{"id":"60174","area":{"x":1,"y":8,"z":24},"centroid":{"x":1289,"y":5140,"z":1419},"post":{"x":1288,"y":5134,"z":1417},"pre":{"x":1291,"y":5146,"z":1421}},{"id":"60174","area":{"x":2,"y":14,"z":2},"centroid":{"x":1318,"y":4980,"z":1417},"post":{"x":1316,"y":4980,"z":1416},"pre":{"x":1321,"y":4981,"z":1419}},{"id":"70131","area":{"x":10,"y":17,"z":45},"centroid":{"x":1356,"y":5157,"z":1296},"post":{"x":1353,"y":5153,"z":1294},"pre":{"x":1360,"y":5163,"z":1299}},{"id":"60174","area":{"x":28,"y":15,"z":63},"centroid":{"x":1342,"y":4823,"z":1508},"post":{"x":1338,"y":4816,"z":1503},"pre":{"x":1347,"y":4831,"z":1511}},{"id":"70068","area":{"x":51,"y":32,"z":110},"centroid":{"x":1391,"y":4981,"z":1413},"post":{"x":1386,"y":4973,"z":1408},"pre":{"x":1397,"y":4987,"z":1417}},{"id":"70090","area":{"x":49,"y":30,"z":12},"centroid":{"x":1362,"y":5423,"z":1320},"post":{"x":1360,"y":5419,"z":1313},"pre":{"x":1367,"y":5429,"z":1328}},{"id":"70159","area":{"x":14,"y":13,"z":40},"centroid":{"x":1503,"y":5213,"z":1289},"post":{"x":1496,"y":5207,"z":1288},"pre":{"x":1506,"y":5218,"z":1291}},{"id":"70128","area":{"x":58,"y":40,"z":236},"centroid":{"x":1413,"y":5182,"z":1312},"post":{"x":1408,"y":5164,"z":1311},"pre":{"x":1423,"y":5201,"z":1317}},{"id":"70128","area":{"x":40,"y":10,"z":32},"centroid":{"x":1420,"y":5153,"z":1313},"post":{"x":1419,"y":5140,"z":1311},"pre":{"x":1423,"y":5160,"z":1316}},{"id":"60211","area":{"x":113,"y":79,"z":248},"centroid":{"x":1365,"y":5432,"z":1322},"post":{"x":1353,"y":5422,"z":1314},"pre":{"x":1382,"y":5442,"z":1330}},{"id":"70152","area":{"x":140,"y":107,"z":138},"centroid":{"x":1359,"y":5135,"z":1307},"post":{"x":1352,"y":5120,"z":1298},"pre":{"x":1368,"y":5154,"z":1316}},{"id":"70152","area":{"x":5,"y":7,"z":2},"centroid":{"x":1408,"y":4971,"z":1418},"post":{"x":1406,"y":4970,"z":1417},"pre":{"x":1410,"y":4973,"z":1419}},{"id":"70152","area":{"x":7,"y":4,"z":5},"centroid":{"x":1409,"y":4973,"z":1423},"post":{"x":1407,"y":4970,"z":1423},"pre":{"x":1411,"y":4975,"z":1424}},{"id":"70158","area":{"x":144,"y":18,"z":87},"centroid":{"x":1356,"y":5287,"z":1307},"post":{"x":1355,"y":5265,"z":1304},"pre":{"x":1360,"y":5306,"z":1310}},{"id":"90002","area":{"x":76,"y":117,"z":222},"centroid":{"x":1304,"y":5067,"z":1159},"post":{"x":1292,"y":5056,"z":1155},"pre":{"x":1318,"y":5078,"z":1166}},{"id":"70148","area":{"x":128,"y":131,"z":298},"centroid":{"x":1396,"y":4965,"z":1419},"post":{"x":1384,"y":4951,"z":1411},"pre":{"x":1409,"y":4979,"z":1426}},{"id":"60174","area":{"x":140,"y":82,"z":50},"centroid":{"x":1340,"y":5084,"z":1311},"post":{"x":1338,"y":5074,"z":1303},"pre":{"x":1347,"y":5091,"z":1318}},{"id":"60174","area":{"x":39,"y":44,"z":44},"centroid":{"x":1355,"y":5024,"z":1316},"post":{"x":1350,"y":5017,"z":1312},"pre":{"x":1362,"y":5031,"z":1320}},{"id":"60174","area":{"x":24,"y":11,"z":32},"centroid":{"x":1391,"y":5135,"z":1431},"post":{"x":1388,"y":5132,"z":1428},"pre":{"x":1396,"y":5138,"z":1434}},{"id":"90002","area":{"x":128,"y":78,"z":69},"centroid":{"x":1401,"y":4969,"z":1429},"post":{"x":1395,"y":4955,"z":1421},"pre":{"x":1407,"y":4979,"z":1436}},{"id":"60198","area":{"x":183,"y":377,"z":178},"centroid":{"x":1346,"y":5142,"z":1406},"post":{"x":1327,"y":5134,"z":1391},"pre":{"x":1373,"y":5149,"z":1424}},{"id":"90002","area":{"x":130,"y":100,"z":73},"centroid":{"x":1403,"y":4943,"z":1439},"post":{"x":1401,"y":4929,"z":1430},"pre":{"x":1409,"y":4953,"z":1451}},{"id":"90002","area":{"x":0,"y":0,"z":3},"centroid":{"x":1416,"y":5178,"z":1318},"post":{"x":1416,"y":5177,"z":1318},"pre":{"x":1416,"y":5179,"z":1318}},{"id":"60198","area":{"x":14,"y":14,"z":131},"centroid":{"x":1353,"y":5282,"z":1321},"post":{"x":1348,"y":5271,"z":1317},"pre":{"x":1359,"y":5297,"z":1323}},{"id":"60198","area":{"x":153,"y":71,"z":214},"centroid":{"x":1366,"y":5146,"z":1309},"post":{"x":1360,"y":5134,"z":1304},"pre":{"x":1374,"y":5160,"z":1317}},{"id":"60198","area":{"x":134,"y":213,"z":127},"centroid":{"x":1387,"y":5130,"z":1420},"post":{"x":1379,"y":5125,"z":1411},"pre":{"x":1396,"y":5140,"z":1432}},{"id":"60198","area":{"x":6,"y":13,"z":48},"centroid":{"x":1414,"y":5176,"z":1261},"post":{"x":1411,"y":5172,"z":1260},"pre":{"x":1417,"y":5181,"z":1263}},{"id":"60198","area":{"x":31,"y":63,"z":236},"centroid":{"x":1425,"y":5191,"z":1271},"post":{"x":1415,"y":5182,"z":1267},"pre":{"x":1439,"y":5200,"z":1274}},{"id":"60198","area":{"x":7,"y":12,"z":36},"centroid":{"x":1430,"y":5118,"z":1314},"post":{"x":1427,"y":5115,"z":1313},"pre":{"x":1433,"y":5122,"z":1317}}]
