[{"id":"60078","area":{"x":23,"y":78,"z":18},"centroid":{"x":1592,"y":4556,"z":3413},"post":{"x":1589,"y":4554,"z":3408},"pre":{"x":1597,"y":4560,"z":3420}},{"id":"60080","area":{"x":8,"y":3,"z":32},"centroid":{"x":1440,"y":4327,"z":3161},"post":{"x":1438,"y":4324,"z":3161},"pre":{"x":1444,"y":4331,"z":3163}},{"id":"60028","area":{"x":23,"y":24,"z":76},"centroid":{"x":1434,"y":4323,"z":3164},"post":{"x":1430,"y":4318,"z":3161},"pre":{"x":1440,"y":4329,"z":3167}},{"id":"60114","area":{"x":12,"y":35,"z":40},"centroid":{"x":1500,"y":4160,"z":3169},"post":{"x":1498,"y":4154,"z":3164},"pre":{"x":1503,"y":4167,"z":3175}},{"id":"60132","area":{"x":1,"y":16,"z":16},"centroid":{"x":1401,"y":4028,"z":3168},"post":{"x":1399,"y":4027,"z":3167},"pre":{"x":1405,"y":4031,"z":3170}},{"id":"60132","area":{"x":0,"y":14,"z":5},"centroid":{"x":1522,"y":3920,"z":3225},"post":{"x":1520,"y":3920,"z":3224},"pre":{"x":1525,"y":3921,"z":3226}},{"id":"60132","area":{"x":0,"y":0,"z":8},"centroid":{"x":1588,"y":4008,"z":3325},"post":{"x":1587,"y":4007,"z":3325},"pre":{"x":1589,"y":4009,"z":3325}},{"id":"60114","area":{"x":94,"y":63,"z":63},"centroid":{"x":1527,"y":4161,"z":3108},"post":{"x":1520,"y":4151,"z":3105},"pre":{"x":1533,"y":4176,"z":3113}},{"id":"60114","area":{"x":0,"y":0,"z":4},"centroid":{"x":1539,"y":4168,"z":3119},"post":{"x":1538,"y":4168,"z":3119},"pre":{"x":1540,"y":4169,"z":3119}},{"id":"60156","area":{"x":1,"y":13,"z":18},"centroid":{"x":1395,"y":4023,"z":3231},"post":{"x":1392,"y":4021,"z":3229},"pre":{"x":1398,"y":4026,"z":3233}},{"id":"60156","area":{"x":29,"y":25,"z":6},"centroid":{"x":1411,"y":3943,"z":3264},"post":{"x":1409,"y":3940,"z":3262},"pre":{"x":1415,"y":3948,"z":3266}},{"id":"60087","area":{"x":16,"y":40,"z":71},"centroid":{"x":1383,"y":4102,"z":3242},"post":{"x":1378,"y":4098,"z":3239},"pre":{"x":1389,"y":4107,"z":3245}},{"id":"60194","area":{"x":44,"y":13,"z":21},"centroid":{"x":1430,"y":4347,"z":3248},"post":{"x":1429,"y":4344,"z":3245},"pre":{"x":1434,"y":4350,"z":3254}},{"id":"60194","area":{"x":70,"y":31,"z":128},"centroid":{"x":1439,"y":4312,"z":3184},"post":{"x":1432,"y":4305,"z":3180},"pre":{"x":1447,"y":4321,"z":3188}},{"id":"60030","area":{"x":49,"y":17,"z":49},"centroid":{"x":1355,"y":4072,"z":3158},"post":{"x":1352,"y":4067,"z":3154},"pre":{"x":1360,"y":4079,"z":3162}},{"id":"60112","area":{"x":43,"y":41,"z":96},"centroid":{"x":1420,"y":4192,"z":3345},"post":{"x":1416,"y":4182,"z":3341},"pre":{"x":1425,"y":4204,"z":3348}},{"id":"60112","area":{"x":0,"y":2,"z":2},"centroid":{"x":1423,"y":4193,"z":3332},"post":{"x":1422,"y":4193,"z":3332},"pre":{"x":1424,"y":4194,"z":3333}},{"id":"60112","area":{"x":15,"y":2,"z":1},"centroid":{"x":1427,"y":4186,"z":3330},"post":{"x":1427,"y":4184,"z":3329},"pre":{"x":1428,"y":4189,"z":3332}},{"id":"60080","area":{"x":13,"y":19,"z":24},"centroid":{"x":1605,"y":4324,"z":3395},"post":{"x":1602,"y":4319,"z":3393},"pre":{"x":1608,"y":4327,"z":3398}},{"id":"60080","area":{"x":5,"y":6,"z":17},"centroid":{"x":1621,"y":4292,"z":3388},"post":{"x":1619,"y":4290,"z":3387},"pre":{"x":1623,"y":4294,"z":3389}},{"id":"60112","area":{"x":4,"y":22,"z":21},"centroid":{"x":1461,"y":4005,"z":3276},"post":{"x":1459,"y":4003,"z":3274},"pre":{"x":1465,"y":4009,"z":3278}},{"id":"60112","area":{"x":26,"y":9,"z":10},"centroid":{"x":1631,"y":4196,"z":3435},"post":{"x":1630,"y":4192,"z":3433},"pre":{"x":1633,"y":4200,"z":3437}},{"id":"60201","area":{"x":1,"y":34,"z":70},"centroid":{"x":1437,"y":4325,"z":3259},"post":{"x":1433,"y":4321,"z":3256},"pre":{"x":1442,"y":4335,"z":3261}},{"id":"60199","area":{"x":18,"y":40,"z":73},"centroid":{"x":1362,"y":4057,"z":3169},"post":{"x":1356,"y":4055,"z":3167},"pre":{"x":1371,"y":4063,"z":3173}},{"id":"60199","area":{"x":4,"y":9,"z":28},"centroid":{"x":1377,"y":4086,"z":3177},"post":{"x":1375,"y":4084,"z":3175},"pre":{"x":1381,"y":4089,"z":3179}},{"id":"60430","area":{"x":19,"y":5,"z":96},"centroid":{"x":1420,"y":4208,"z":3181},"post":{"x":1417,"y":4203,"z":3181},"pre":{"x":1427,"y":4215,"z":3183}},{"id":"60199","area":{"x":4,"y":10,"z":40},"centroid":{"x":1395,"y":4133,"z":3164},"post":{"x":1391,"y":4131,"z":3164},"pre":{"x":1399,"y":4136,"z":3167}},{"id":"60154","area":{"x":2,"y":24,"z":0},"centroid":{"x":1351,"y":4068,"z":3151},"post":{"x":1347,"y":4068,"z":3149},"pre":{"x":1355,"y":4070,"z":3153}},{"id":"60194","area":{"x":0,"y":22,"z":7},"centroid":{"x":1568,"y":4144,"z":3276},"post":{"x":1566,"y":4143,"z":3274},"pre":{"x":1570,"y":4145,"z":3280}},{"id":"60194","area":{"x":0,"y":6,"z":0},"centroid":{"x":1594,"y":4223,"z":3287},"post":{"x":1593,"y":4223,"z":3286},"pre":{"x":1595,"y":4223,"z":3288}},{"id":"60194","area":{"x":8,"y":35,"z":43},"centroid":{"x":1601,"y":4217,"z":3296},"post":{"x":1596,"y":4214,"z":3294},"pre":{"x":1606,"y":4221,"z":3299}},{"id":"70019","area":{"x":2,"y":31,"z":7},"centroid":{"x":1570,"y":4021,"z":3185},"post":{"x":1566,"y":4020,"z":3183},"pre":{"x":1574,"y":4023,"z":3189}},{"id":"70023","area":{"x":6,"y":37,"z":14},"centroid":{"x":1485,"y":4005,"z":3254},"post":{"x":1482,"y":4004,"z":3251},"pre":{"x":1489,"y":4008,"z":3257}},{"id":"60030","area":{"x":69,"y":62,"z":235},"centroid":{"x":1375,"y":4107,"z":3174},"post":{"x":1361,"y":4096,"z":3168},"pre":{"x":1388,"y":4121,"z":3180}},{"id":"60030","area":{"x":1,"y":12,"z":15},"centroid":{"x":1382,"y":4105,"z":3247},"post":{"x":1381,"y":4103,"z":3246},"pre":{"x":1385,"y":4107,"z":3249}},{"id":"60030","area":{"x":0,"y":13,"z":2},"centroid":{"x":1385,"y":4100,"z":3254},"post":{"x":1383,"y":4100,"z":3253},"pre":{"x":1387,"y":4101,"z":3256}},{"id":"60183","area":{"x":176,"y":135,"z":117},"centroid":{"x":1447,"y":3956,"z":3206},"post":{"x":1434,"y":3946,"z":3200},"pre":{"x":1460,"y":3969,"z":3215}},{"id":"60087","area":{"x":48,"y":213,"z":75},"centroid":{"x":1431,"y":4087,"z":3237},"post":{"x":1420,"y":4083,"z":3224},"pre":{"x":1441,"y":4090,"z":3247}},{"id":"70030","area":{"x":20,"y":43,"z":55},"centroid":{"x":1425,"y":4323,"z":3183},"post":{"x":1420,"y":4321,"z":3182},"pre":{"x":1431,"y":4327,"z":3187}},{"id":"60388","area":{"x":48,"y":100,"z":198},"centroid":{"x":1467,"y":4322,"z":3365},"post":{"x":1450,"y":4317,"z":3361},"pre":{"x":1489,"y":4330,"z":3370}},{"id":"70033","area":{"x":7,"y":16,"z":7},"centroid":{"x":1420,"y":4095,"z":3210},"post":{"x":1418,"y":4093,"z":3206},"pre":{"x":1424,"y":4097,"z":3214}},{"id":"70016","area":{"x":56,"y":13,"z":52},"centroid":{"x":1418,"y":4214,"z":3183},"post":{"x":1416,"y":4205,"z":3181},"pre":{"x":1424,"y":4223,"z":3188}},{"id":"70016","area":{"x":2,"y":27,"z":14},"centroid":{"x":1476,"y":3974,"z":3218},"post":{"x":1472,"y":3972,"z":3215},"pre":{"x":1480,"y":3976,"z":3221}},{"id":"70024","area":{"x":26,"y":5,"z":9},"centroid":{"x":1408,"y":4147,"z":3191},"post":{"x":1406,"y":4144,"z":3188},"pre":{"x":1410,"y":4153,"z":3194}},{"id":"70044","area":{"x":47,"y":67,"z":64},"centroid":{"x":1400,"y":4138,"z":3166},"post":{"x":1393,"y":4131,"z":3163},"pre":{"x":1409,"y":4147,"z":3174}},{"id":"70024","area":{"x":10,"y":26,"z":15},"centroid":{"x":1419,"y":4057,"z":3172},"post":{"x":1415,"y":4051,"z":3170},"pre":{"x":1426,"y":4061,"z":3175}},{"id":"70031","area":{"x":38,"y":42,"z":17},"centroid":{"x":1434,"y":4165,"z":3203},"post":{"x":1428,"y":4159,"z":3200},"pre":{"x":1440,"y":4171,"z":3206}},{"id":"60156","area":{"x":83,"y":117,"z":109},"centroid":{"x":1453,"y":3953,"z":3215},"post":{"x":1434,"y":3942,"z":3210},"pre":{"x":1470,"y":3969,"z":3225}},{"id":"70025","area":{"x":44,"y":25,"z":59},"centroid":{"x":1417,"y":4157,"z":3189},"post":{"x":1414,"y":4144,"z":3182},"pre":{"x":1421,"y":4174,"z":3194}},{"id":"70014","area":{"x":11,"y":31,"z":69},"centroid":{"x":1421,"y":4029,"z":3272},"post":{"x":1415,"y":4025,"z":3270},"pre":{"x":1429,"y":4036,"z":3274}},{"id":"70014","area":{"x":4,"y":13,"z":38},"centroid":{"x":1417,"y":4246,"z":3176},"post":{"x":1415,"y":4240,"z":3175},"pre":{"x":1422,"y":4254,"z":3180}},{"id":"70014","area":{"x":2,"y":2,"z":11},"centroid":{"x":1429,"y":4034,"z":3266},"post":{"x":1427,"y":4033,"z":3266},"pre":{"x":1431,"y":4035,"z":3268}},{"id":"60087","area":{"x":14,"y":18,"z":107},"centroid":{"x":1435,"y":4174,"z":3206},"post":{"x":1429,"y":4167,"z":3204},"pre":{"x":1440,"y":4180,"z":3209}},{"id":"60087","area":{"x":13,"y":5,"z":0},"centroid":{"x":1440,"y":4094,"z":3227},"post":{"x":1439,"y":4094,"z":3225},"pre":{"x":1442,"y":4096,"z":3231}},{"id":"60087","area":{"x":3,"y":46,"z":6},"centroid":{"x":1445,"y":4161,"z":3324},"post":{"x":1440,"y":4161,"z":3321},"pre":{"x":1450,"y":4163,"z":3328}},{"id":"60087","area":{"x":3,"y":8,"z":4},"centroid":{"x":1451,"y":4068,"z":3276},"post":{"x":1450,"y":4068,"z":3275},"pre":{"x":1453,"y":4070,"z":3278}},{"id":"60087","area":{"x":0,"y":12,"z":5},"centroid":{"x":1684,"y":4163,"z":3332},"post":{"x":1682,"y":4162,"z":3331},"pre":{"x":1686,"y":4164,"z":3334}},{"id":"70034","area":{"x":42,"y":32,"z":83},"centroid":{"x":1421,"y":4080,"z":3244},"post":{"x":1417,"y":4071,"z":3240},"pre":{"x":1427,"y":4088,"z":3248}},{"id":"70034","area":{"x":41,"y":49,"z":71},"centroid":{"x":1423,"y":4028,"z":3265},"post":{"x":1418,"y":4025,"z":3261},"pre":{"x":1432,"y":4033,"z":3271}},{"id":"70033","area":{"x":31,"y":129,"z":145},"centroid":{"x":1438,"y":4053,"z":3170},"post":{"x":1428,"y":4039,"z":3154},"pre":{"x":1448,"y":4073,"z":3182}},{"id":"60430","area":{"x":85,"y":209,"z":153},"centroid":{"x":1561,"y":4213,"z":3141},"post":{"x":1549,"y":4207,"z":3126},"pre":{"x":1572,"y":4225,"z":3153}},{"id":"70066","area":{"x":8,"y":5,"z":0},"centroid":{"x":1420,"y":4325,"z":3179},"post":{"x":1420,"y":4324,"z":3177},"pre":{"x":1422,"y":4327,"z":3181}},{"id":"70024","area":{"x":37,"y":55,"z":74},"centroid":{"x":1421,"y":4038,"z":3175},"post":{"x":1417,"y":4032,"z":3171},"pre":{"x":1428,"y":4046,"z":3179}},{"id":"70014","area":{"x":29,"y":37,"z":25},"centroid":{"x":1432,"y":4171,"z":3191},"post":{"x":1428,"y":4167,"z":3188},"pre":{"x":1438,"y":4177,"z":3195}},{"id":"70068","area":{"x":22,"y":31,"z":34},"centroid":{"x":1414,"y":4073,"z":3253},"post":{"x":1409,"y":4071,"z":3245},"pre":{"x":1423,"y":4078,"z":3259}},{"id":"70014","area":{"x":52,"y":23,"z":83},"centroid":{"x":1435,"y":4291,"z":3246},"post":{"x":1433,"y":4279,"z":3244},"pre":{"x":1441,"y":4301,"z":3250}},{"id":"70014","area":{"x":0,"y":0,"z":3},"centroid":{"x":1434,"y":4034,"z":3268},"post":{"x":1434,"y":4034,"z":3268},"pre":{"x":1435,"y":4035,"z":3268}},{"id":"70014","area":{"x":10,"y":9,"z":3},"centroid":{"x":1439,"y":4159,"z":3197},"post":{"x":1438,"y":4157,"z":3196},"pre":{"x":1441,"y":4161,"z":3199}},{"id":"60030","area":{"x":109,"y":70,"z":45},"centroid":{"x":1390,"y":4140,"z":3169},"post":{"x":1386,"y":4131,"z":3164},"pre":{"x":1398,"y":4151,"z":3173}},{"id":"70014","area":{"x":63,"y":8,"z":13},"centroid":{"x":1443,"y":4048,"z":3265},"post":{"x":1441,"y":4044,"z":3261},"pre":{"x":1445,"y":4054,"z":3270}},{"id":"70068","area":{"x":86,"y":44,"z":69},"centroid":{"x":1422,"y":4083,"z":3208},"post":{"x":1418,"y":4074,"z":3206},"pre":{"x":1428,"y":4094,"z":3212}},{"id":"70048","area":{"x":107,"y":45,"z":66},"centroid":{"x":1433,"y":4333,"z":3255},"post":{"x":1430,"y":4325,"z":3248},"pre":{"x":1440,"y":4341,"z":3260}},{"id":"70048","area":{"x":3,"y":20,"z":2},"centroid":{"x":1461,"y":3947,"z":3212},"post":{"x":1459,"y":3946,"z":3207},"pre":{"x":1463,"y":3949,"z":3217}},{"id":"70068","area":{"x":35,"y":11,"z":21},"centroid":{"x":1432,"y":4054,"z":3211},"post":{"x":1431,"y":4048,"z":3209},"pre":{"x":1434,"y":4060,"z":3215}},{"id":"60199","area":{"x":168,"y":114,"z":171},"centroid":{"x":1421,"y":4051,"z":3167},"post":{"x":1413,"y":4035,"z":3164},"pre":{"x":1429,"y":4069,"z":3173}},{"id":"60199","area":{"x":21,"y":9,"z":33},"centroid":{"x":1421,"y":4224,"z":3183},"post":{"x":1417,"y":4219,"z":3181},"pre":{"x":1425,"y":4230,"z":3185}},{"id":"60199","area":{"x":4,"y":2,"z":0},"centroid":{"x":1477,"y":4178,"z":3197},"post":{"x":1477,"y":4178,"z":3197},"pre":{"x":1478,"y":4179,"z":3198}},{"id":"60199","area":{"x":6,"y":1,"z":4},"centroid":{"x":1488,"y":4176,"z":3194},"post":{"x":1487,"y":4175,"z":3194},"pre":{"x":1489,"y":4178,"z":3195}},{"id":"60199","area":{"x":4,"y":1,"z":12},"centroid":{"x":1521,"y":4151,"z":3110},"post":{"x":1520,"y":4150,"z":3110},"pre":{"x":1523,"y":4154,"z":3111}},{"id":"60154","area":{"x":90,"y":84,"z":285},"centroid":{"x":1361,"y":4056,"z":3164},"post":{"x":1352,"y":4041,"z":3157},"pre":{"x":1372,"y":4068,"z":3168}},{"id":"70079","area":{"x":23,"y":2,"z":8},"centroid":{"x":1443,"y":4155,"z":3207},"post":{"x":1443,"y":4153,"z":3204},"pre":{"x":1444,"y":4158,"z":3210}},{"id":"70038","area":{"x":130,"y":269,"z":118},"centroid":{"x":1515,"y":4178,"z":3205},"post":{"x":1505,"y":4170,"z":3185},"pre":{"x":1526,"y":4192,"z":3220}},{"id":"70084","area":{"x":5,"y":4,"z":6},"centroid":{"x":1414,"y":4249,"z":3175},"post":{"x":1413,"y":4248,"z":3175},"pre":{"x":1416,"y":4252,"z":3177}},{"id":"70024","area":{"x":29,"y":113,"z":93},"centroid":{"x":1430,"y":4183,"z":3199},"post":{"x":1423,"y":4178,"z":3194},"pre":{"x":1439,"y":4192,"z":3204}},{"id":"70024","area":{"x":32,"y":39,"z":13},"centroid":{"x":1438,"y":4163,"z":3326},"post":{"x":1433,"y":4161,"z":3320},"pre":{"x":1444,"y":4168,"z":3335}},{"id":"70024","area":{"x":5,"y":1,"z":1},"centroid":{"x":1445,"y":4133,"z":3202},"post":{"x":1445,"y":4133,"z":3201},"pre":{"x":1446,"y":4134,"z":3203}},{"id":"70024","area":{"x":0,"y":0,"z":2},"centroid":{"x":1447,"y":4137,"z":3207},"post":{"x":1447,"y":4137,"z":3207},"pre":{"x":1447,"y":4138,"z":3207}},{"id":"70109","area":{"x":18,"y":19,"z":48},"centroid":{"x":1355,"y":4071,"z":3164},"post":{"x":1353,"y":4063,"z":3162},"pre":{"x":1357,"y":4077,"z":3167}},{"id":"70033","area":{"x":69,"y":28,"z":34},"centroid":{"x":1431,"y":4340,"z":3250},"post":{"x":1429,"y":4335,"z":3245},"pre":{"x":1435,"y":4345,"z":3258}},{"id":"70033","area":{"x":9,"y":69,"z":24},"centroid":{"x":1436,"y":4329,"z":3171},"post":{"x":1431,"y":4325,"z":3162},"pre":{"x":1442,"y":4332,"z":3184}},{"id":"70063","area":{"x":50,"y":69,"z":184},"centroid":{"x":1607,"y":4426,"z":3445},"post":{"x":1604,"y":4407,"z":3435},"pre":{"x":1613,"y":4443,"z":3453}},{"id":"70117","area":{"x":31,"y":10,"z":22},"centroid":{"x":1414,"y":4162,"z":3192},"post":{"x":1412,"y":4157,"z":3189},"pre":{"x":1417,"y":4168,"z":3196}},{"id":"70117","area":{"x":5,"y":5,"z":7},"centroid":{"x":1472,"y":3943,"z":3222},"post":{"x":1471,"y":3942,"z":3221},"pre":{"x":1474,"y":3945,"z":3224}},{"id":"70025","area":{"x":226,"y":47,"z":166},"centroid":{"x":1427,"y":4079,"z":3217},"post":{"x":1420,"y":4057,"z":3211},"pre":{"x":1433,"y":4097,"z":3224}},{"id":"70025","area":{"x":0,"y":0,"z":5},"centroid":{"x":1463,"y":3949,"z":3225},"post":{"x":1463,"y":3948,"z":3225},"pre":{"x":1464,"y":3950,"z":3225}},{"id":"70096","area":{"x":22,"y":8,"z":8},"centroid":{"x":1382,"y":4002,"z":3267},"post":{"x":1380,"y":4000,"z":3266},"pre":{"x":1383,"y":4006,"z":3270}},{"id":"70077","area":{"x":4,"y":40,"z":71},"centroid":{"x":1443,"y":4010,"z":3249},"post":{"x":1440,"y":4001,"z":3243},"pre":{"x":1446,"y":4026,"z":3257}},{"id":"70096","area":{"x":80,"y":68,"z":66},"centroid":{"x":1394,"y":4023,"z":3235},"post":{"x":1389,"y":4013,"z":3228},"pre":{"x":1403,"y":4035,"z":3247}},{"id":"70014","area":{"x":12,"y":1,"z":31},"centroid":{"x":1459,"y":4074,"z":3173},"post":{"x":1456,"y":4071,"z":3172},"pre":{"x":1463,"y":4079,"z":3175}},{"id":"70014","area":{"x":37,"y":24,"z":18},"centroid":{"x":1461,"y":4257,"z":3204},"post":{"x":1458,"y":4252,"z":3202},"pre":{"x":1466,"y":4265,"z":3206}},{"id":"70014","area":{"x":55,"y":13,"z":28},"centroid":{"x":1470,"y":4204,"z":3154},"post":{"x":1468,"y":4197,"z":3149},"pre":{"x":1474,"y":4212,"z":3161}},{"id":"70133","area":{"x":11,"y":35,"z":120},"centroid":{"x":1417,"y":4058,"z":3203},"post":{"x":1409,"y":4052,"z":3201},"pre":{"x":1426,"y":4066,"z":3207}},{"id":"70133","area":{"x":2,"y":2,"z":6},"centroid":{"x":1418,"y":4090,"z":3213},"post":{"x":1418,"y":4090,"z":3213},"pre":{"x":1419,"y":4092,"z":3214}},{"id":"70133","area":{"x":33,"y":5,"z":0},"centroid":{"x":1427,"y":4065,"z":3224},"post":{"x":1426,"y":4062,"z":3222},"pre":{"x":1428,"y":4071,"z":3227}},{"id":"70109","area":{"x":48,"y":20,"z":126},"centroid":{"x":1400,"y":4072,"z":3201},"post":{"x":1390,"y":4063,"z":3198},"pre":{"x":1409,"y":4078,"z":3206}},{"id":"70033","area":{"x":68,"y":158,"z":51},"centroid":{"x":1466,"y":4336,"z":3372},"post":{"x":1459,"y":4333,"z":3359},"pre":{"x":1473,"y":4340,"z":3385}},{"id":"70109","area":{"x":28,"y":1,"z":10},"centroid":{"x":1414,"y":4020,"z":3245},"post":{"x":1413,"y":4016,"z":3243},"pre":{"x":1415,"y":4025,"z":3248}},{"id":"70109","area":{"x":6,"y":6,"z":1},"centroid":{"x":1431,"y":3974,"z":3277},"post":{"x":1429,"y":3973,"z":3277},"pre":{"x":1432,"y":3976,"z":3279}},{"id":"70148","area":{"x":13,"y":34,"z":21},"centroid":{"x":1409,"y":4073,"z":3255},"post":{"x":1406,"y":4071,"z":3250},"pre":{"x":1414,"y":4076,"z":3261}},{"id":"70127","area":{"x":59,"y":56,"z":86},"centroid":{"x":1383,"y":4098,"z":3249},"post":{"x":1377,"y":4093,"z":3244},"pre":{"x":1390,"y":4104,"z":3255}},{"id":"70154","area":{"x":2,"y":23,"z":3},"centroid":{"x":1412,"y":4138,"z":3183},"post":{"x":1411,"y":4137,"z":3180},"pre":{"x":1414,"y":4139,"z":3186}},{"id":"70077","area":{"x":103,"y":41,"z":35},"centroid":{"x":1445,"y":4074,"z":3227},"post":{"x":1440,"y":4063,"z":3220},"pre":{"x":1453,"y":4083,"z":3235}},{"id":"70077","area":{"x":3,"y":1,"z":2},"centroid":{"x":1443,"y":4083,"z":3215},"post":{"x":1442,"y":4082,"z":3215},"pre":{"x":1444,"y":4084,"z":3215}},{"id":"70077","area":{"x":8,"y":29,"z":17},"centroid":{"x":1455,"y":4003,"z":3269},"post":{"x":1453,"y":4000,"z":3265},"pre":{"x":1459,"y":4007,"z":3273}},{"id":"70080","area":{"x":77,"y":18,"z":279},"centroid":{"x":1427,"y":4181,"z":3185},"post":{"x":1421,"y":4169,"z":3182},"pre":{"x":1438,"y":4198,"z":3189}},{"id":"70076","area":{"x":109,"y":182,"z":71},"centroid":{"x":1437,"y":4090,"z":3227},"post":{"x":1425,"y":4087,"z":3206},"pre":{"x":1446,"y":4097,"z":3246}},{"id":"70066","area":{"x":187,"y":102,"z":216},"centroid":{"x":1447,"y":4060,"z":3161},"post":{"x":1439,"y":4040,"z":3154},"pre":{"x":1455,"y":4078,"z":3169}},{"id":"90002","area":{"x":49,"y":12,"z":34},"centroid":{"x":1417,"y":4078,"z":3249},"post":{"x":1416,"y":4072,"z":3247},"pre":{"x":1420,"y":4084,"z":3253}},{"id":"70066","area":{"x":62,"y":42,"z":42},"centroid":{"x":1443,"y":4158,"z":3203},"post":{"x":1439,"y":4153,"z":3198},"pre":{"x":1447,"y":4165,"z":3209}},{"id":"70066","area":{"x":0,"y":7,"z":1},"centroid":{"x":1446,"y":4186,"z":3328},"post":{"x":1445,"y":4186,"z":3326},"pre":{"x":1447,"y":4187,"z":3330}},{"id":"70066","area":{"x":3,"y":1,"z":7},"centroid":{"x":1446,"y":4136,"z":3196},"post":{"x":1446,"y":4135,"z":3196},"pre":{"x":1447,"y":4138,"z":3197}},{"id":"70066","area":{"x":18,"y":2,"z":6},"centroid":{"x":1447,"y":4179,"z":3218},"post":{"x":1446,"y":4176,"z":3217},"pre":{"x":1448,"y":4182,"z":3221}},{"id":"60030","area":{"x":106,"y":53,"z":64},"centroid":{"x":1392,"y":4035,"z":3238},"post":{"x":1388,"y":4026,"z":3231},"pre":{"x":1396,"y":4042,"z":3244}},{"id":"70114","area":{"x":170,"y":150,"z":152},"centroid":{"x":1430,"y":4069,"z":3234},"post":{"x":1423,"y":4050,"z":3213},"pre":{"x":1435,"y":4083,"z":3245}},{"id":"60030","area":{"x":15,"y":76,"z":10},"centroid":{"x":1401,"y":4070,"z":3256},"post":{"x":1394,"y":4068,"z":3249},"pre":{"x":1408,"y":4073,"z":3260}},{"id":"70151","area":{"x":22,"y":32,"z":24},"centroid":{"x":1413,"y":4081,"z":3251},"post":{"x":1411,"y":4077,"z":3246},"pre":{"x":1416,"y":4086,"z":3256}},{"id":"70151","area":{"x":5,"y":10,"z":105},"centroid":{"x":1453,"y":4063,"z":3160},"post":{"x":1445,"y":4048,"z":3159},"pre":{"x":1460,"y":4078,"z":3163}},{"id":"70128","area":{"x":123,"y":76,"z":47},"centroid":{"x":1392,"y":4021,"z":3255},"post":{"x":1388,"y":4016,"z":3243},"pre":{"x":1398,"y":4031,"z":3269}},{"id":"70128","area":{"x":45,"y":40,"z":21},"centroid":{"x":1413,"y":4142,"z":3187},"post":{"x":1409,"y":4139,"z":3182},"pre":{"x":1417,"y":4145,"z":3194}},{"id":"60030","area":{"x":57,"y":14,"z":56},"centroid":{"x":1418,"y":4082,"z":3197},"post":{"x":1413,"y":4078,"z":3191},"pre":{"x":1425,"y":4086,"z":3203}},{"id":"70121","area":{"x":108,"y":56,"z":305},"centroid":{"x":1419,"y":4071,"z":3204},"post":{"x":1407,"y":4048,"z":3202},"pre":{"x":1433,"y":4090,"z":3210}},{"id":"70127","area":{"x":62,"y":75,"z":19},"centroid":{"x":1413,"y":4045,"z":3160},"post":{"x":1401,"y":4042,"z":3151},"pre":{"x":1422,"y":4052,"z":3174}},{"id":"70076","area":{"x":11,"y":42,"z":137},"centroid":{"x":1441,"y":4060,"z":3175},"post":{"x":1435,"y":4046,"z":3168},"pre":{"x":1448,"y":4076,"z":3181}},{"id":"70154","area":{"x":37,"y":56,"z":68},"centroid":{"x":1423,"y":4190,"z":3340},"post":{"x":1418,"y":4185,"z":3334},"pre":{"x":1432,"y":4196,"z":3344}},{"id":"70049","area":{"x":269,"y":31,"z":135},"centroid":{"x":1416,"y":4237,"z":3183},"post":{"x":1413,"y":4214,"z":3175},"pre":{"x":1420,"y":4266,"z":3189}},{"id":"70137","area":{"x":30,"y":74,"z":202},"centroid":{"x":1427,"y":4058,"z":3173},"post":{"x":1420,"y":4042,"z":3164},"pre":{"x":1435,"y":4071,"z":3180}},{"id":"70137","area":{"x":2,"y":17,"z":3},"centroid":{"x":1458,"y":4338,"z":3366},"post":{"x":1457,"y":4338,"z":3364},"pre":{"x":1460,"y":4340,"z":3369}},{"id":"70154","area":{"x":33,"y":102,"z":13},"centroid":{"x":1430,"y":4328,"z":3172},"post":{"x":1422,"y":4327,"z":3161},"pre":{"x":1436,"y":4332,"z":3181}},{"id":"70049","area":{"x":58,"y":11,"z":5},"centroid":{"x":1419,"y":4198,"z":3185},"post":{"x":1417,"y":4193,"z":3182},"pre":{"x":1421,"y":4205,"z":3189}},{"id":"70154","area":{"x":9,"y":28,"z":22},"centroid":{"x":1479,"y":4007,"z":3253},"post":{"x":1475,"y":4006,"z":3251},"pre":{"x":1483,"y":4010,"z":3258}},{"id":"70049","area":{"x":2,"y":0,"z":1},"centroid":{"x":1422,"y":4247,"z":3186},"post":{"x":1422,"y":4247,"z":3186},"pre":{"x":1423,"y":4248,"z":3187}},{"id":"90002","area":{"x":86,"y":34,"z":51},"centroid":{"x":1420,"y":4186,"z":3188},"post":{"x":1416,"y":4176,"z":3184},"pre":{"x":1423,"y":4194,"z":3195}},{"id":"90002","area":{"x":1,"y":40,"z":90},"centroid":{"x":1427,"y":4033,"z":3273},"post":{"x":1420,"y":4028,"z":3269},"pre":{"x":1434,"y":4038,"z":3275}},{"id":"70128","area":{"x":1,"y":18,"z":27},"centroid":{"x":1423,"y":4030,"z":3177},"post":{"x":1420,"y":4028,"z":3175},"pre":{"x":1426,"y":4033,"z":3179}},{"id":"70051","area":{"x":163,"y":245,"z":264},"centroid":{"x":1380,"y":4035,"z":3167},"post":{"x":1367,"y":4024,"z":3152},"pre":{"x":1392,"y":4051,"z":3177}},{"id":"70066","area":{"x":110,"y":87,"z":124},"centroid":{"x":1458,"y":3958,"z":3213},"post":{"x":1454,"y":3951,"z":3200},"pre":{"x":1467,"y":3966,"z":3226}},{"id":"70146","area":{"x":137,"y":154,"z":283},"centroid":{"x":1436,"y":4068,"z":3214},"post":{"x":1427,"y":4048,"z":3202},"pre":{"x":1450,"y":4088,"z":3223}},{"id":"70127","area":{"x":219,"y":47,"z":174},"centroid":{"x":1436,"y":4013,"z":3252},"post":{"x":1431,"y":4001,"z":3243},"pre":{"x":1443,"y":4025,"z":3260}},{"id":"70127","area":{"x":70,"y":30,"z":20},"centroid":{"x":1441,"y":4067,"z":3224},"post":{"x":1438,"y":4060,"z":3219},"pre":{"x":1445,"y":4075,"z":3232}},{"id":"60030","area":{"x":58,"y":112,"z":263},"centroid":{"x":1431,"y":4298,"z":3175},"post":{"x":1422,"y":4277,"z":3164},"pre":{"x":1443,"y":4320,"z":3180}},{"id":"70146","area":{"x":68,"y":83,"z":51},"centroid":{"x":1454,"y":4178,"z":3319},"post":{"x":1448,"y":4173,"z":3308},"pre":{"x":1462,"y":4183,"z":3328}},{"id":"70146","area":{"x":4,"y":2,"z":17},"centroid":{"x":1451,"y":3958,"z":3201},"post":{"x":1450,"y":3956,"z":3200},"pre":{"x":1454,"y":3961,"z":3202}},{"id":"70125","area":{"x":196,"y":279,"z":409},"centroid":{"x":1396,"y":4005,"z":3264},"post":{"x":1381,"y":3990,"z":3244},"pre":{"x":1414,"y":4019,"z":3275}},{"id":"60030","area":{"x":44,"y":6,"z":65},"centroid":{"x":1433,"y":4080,"z":3212},"post":{"x":1428,"y":4075,"z":3207},"pre":{"x":1441,"y":4084,"z":3216}},{"id":"60030","area":{"x":5,"y":22,"z":6},"centroid":{"x":1441,"y":3967,"z":3210},"post":{"x":1435,"y":3967,"z":3207},"pre":{"x":1447,"y":3970,"z":3215}},{"id":"70031","area":{"x":699,"y":360,"z":506},"centroid":{"x":1444,"y":4042,"z":3254},"post":{"x":1434,"y":4001,"z":3236},"pre":{"x":1455,"y":4069,"z":3270}},{"id":"70049","area":{"x":124,"y":157,"z":141},"centroid":{"x":1439,"y":4343,"z":3252},"post":{"x":1430,"y":4332,"z":3244},"pre":{"x":1448,"y":4351,"z":3259}},{"id":"60154","area":{"x":445,"y":471,"z":616},"centroid":{"x":1366,"y":4107,"z":3184},"post":{"x":1352,"y":4073,"z":3167},"pre":{"x":1388,"y":4129,"z":3195}},{"id":"60030","area":{"x":139,"y":59,"z":123},"centroid":{"x":1454,"y":4271,"z":3238},"post":{"x":1438,"y":4252,"z":3232},"pre":{"x":1466,"y":4295,"z":3247}},{"id":"60030","area":{"x":14,"y":5,"z":11},"centroid":{"x":1440,"y":4060,"z":3214},"post":{"x":1440,"y":4057,"z":3211},"pre":{"x":1442,"y":4065,"z":3217}},{"id":"60154","area":{"x":104,"y":132,"z":66},"centroid":{"x":1385,"y":4076,"z":3247},"post":{"x":1377,"y":4068,"z":3239},"pre":{"x":1396,"y":4094,"z":3258}},{"id":"60154","area":{"x":15,"y":38,"z":46},"centroid":{"x":1392,"y":4037,"z":3246},"post":{"x":1388,"y":4035,"z":3244},"pre":{"x":1397,"y":4041,"z":3250}},{"id":"60030","area":{"x":95,"y":161,"z":28},"centroid":{"x":1460,"y":4177,"z":3225},"post":{"x":1448,"y":4172,"z":3220},"pre":{"x":1468,"y":4183,"z":3232}},{"id":"60030","area":{"x":25,"y":4,"z":98},"centroid":{"x":1462,"y":4039,"z":3233},"post":{"x":1457,"y":4031,"z":3233},"pre":{"x":1466,"y":4047,"z":3236}},{"id":"60030","area":{"x":86,"y":44,"z":21},"centroid":{"x":1461,"y":4059,"z":3164},"post":{"x":1459,"y":4053,"z":3159},"pre":{"x":1467,"y":4064,"z":3169}},{"id":"60030","area":{"x":29,"y":5,"z":125},"centroid":{"x":1476,"y":4042,"z":3240},"post":{"x":1469,"y":4037,"z":3238},"pre":{"x":1484,"y":4049,"z":3243}},{"id":"60030","area":{"x":42,"y":216,"z":166},"centroid":{"x":1542,"y":4032,"z":3244},"post":{"x":1526,"y":4025,"z":3234},"pre":{"x":1556,"y":4040,"z":3254}},{"id":"60030","area":{"x":3,"y":20,"z":15},"centroid":{"x":1566,"y":4130,"z":3271},"post":{"x":1563,"y":4128,"z":3270},"pre":{"x":1570,"y":4132,"z":3274}},{"id":"70049","area":{"x":266,"y":460,"z":316},"centroid":{"x":1460,"y":4175,"z":3205},"post":{"x":1448,"y":4170,"z":3188},"pre":{"x":1482,"y":4184,"z":3219}},{"id":"70051","area":{"x":615,"y":552,"z":653},"centroid":{"x":1392,"y":4094,"z":3190},"post":{"x":1375,"y":4072,"z":3174},"pre":{"x":1428,"y":4122,"z":3207}},{"id":"70049","area":{"x":338,"y":247,"z":476},"centroid":{"x":1475,"y":4325,"z":3375},"post":{"x":1452,"y":4312,"z":3366},"pre":{"x":1493,"y":4340,"z":3388}},{"id":"70051","area":{"x":578,"y":214,"z":700},"centroid":{"x":1406,"y":4080,"z":3243},"post":{"x":1381,"y":4068,"z":3223},"pre":{"x":1429,"y":4098,"z":3255}},{"id":"70049","area":{"x":482,"y":474,"z":279},"centroid":{"x":1466,"y":4255,"z":3219},"post":{"x":1455,"y":4243,"z":3206},"pre":{"x":1480,"y":4270,"z":3234}},{"id":"70049","area":{"x":81,"y":50,"z":67},"centroid":{"x":1484,"y":4335,"z":3394},"post":{"x":1481,"y":4330,"z":3389},"pre":{"x":1491,"y":4343,"z":3400}},{"id":"70051","area":{"x":161,"y":211,"z":230},"centroid":{"x":1398,"y":4138,"z":3177},"post":{"x":1386,"y":4131,"z":3166},"pre":{"x":1410,"y":4151,"z":3191}},{"id":"70051","area":{"x":9,"y":3,"z":3},"centroid":{"x":1390,"y":4097,"z":3249},"post":{"x":1390,"y":4096,"z":3248},"pre":{"x":1391,"y":4098,"z":3252}},{"id":"70051","area":{"x":101,"y":130,"z":97},"centroid":{"x":1399,"y":4036,"z":3236},"post":{"x":1394,"y":4030,"z":3228},"pre":{"x":1405,"y":4041,"z":3247}},{"id":"70051","area":{"x":7,"y":3,"z":3},"centroid":{"x":1410,"y":4155,"z":3189},"post":{"x":1409,"y":4154,"z":3189},"pre":{"x":1412,"y":4157,"z":3191}},{"id":"70049","area":{"x":661,"y":274,"z":307},"centroid":{"x":1494,"y":4171,"z":3174},"post":{"x":1485,"y":4153,"z":3153},"pre":{"x":1506,"y":4186,"z":3194}},{"id":"70049","area":{"x":153,"y":347,"z":670},"centroid":{"x":1551,"y":4194,"z":3231},"post":{"x":1529,"y":4178,"z":3224},"pre":{"x":1575,"y":4215,"z":3238}},{"id":"70049","area":{"x":92,"y":36,"z":44},"centroid":{"x":1590,"y":4203,"z":3236},"post":{"x":1586,"y":4196,"z":3232},"pre":{"x":1594,"y":4209,"z":3243}},{"id":"70051","area":{"x":749,"y":834,"z":1288},"centroid":{"x":1436,"y":4062,"z":3160},"post":{"x":1411,"y":4039,"z":3149},"pre":{"x":1473,"y":4086,"z":3173}},{"id":"70049","area":{"x":134,"y":335,"z":61},"centroid":{"x":1601,"y":4265,"z":3207},"post":{"x":1589,"y":4261,"z":3196},"pre":{"x":1615,"y":4272,"z":3222}},{"id":"70051","area":{"x":257,"y":329,"z":338},"centroid":{"x":1545,"y":4039,"z":3172},"post":{"x":1523,"y":4023,"z":3162},"pre":{"x":1562,"y":4051,"z":3181}},{"id":"70051","area":{"x":249,"y":150,"z":568},"centroid":{"x":1623,"y":4054,"z":3263},"post":{"x":1611,"y":4028,"z":3258},"pre":{"x":1638,"y":4102,"z":3270}},{"id":"70049","area":{"x":424,"y":642,"z":972},"centroid":{"x":1609,"y":4273,"z":3380},"post":{"x":1590,"y":4252,"z":3367},"pre":{"x":1625,"y":4298,"z":3398}},{"id":"70051","area":{"x":229,"y":463,"z":658},"centroid":{"x":1649,"y":4128,"z":3281},"post":{"x":1636,"y":4110,"z":3271},"pre":{"x":1667,"y":4149,"z":3297}},{"id":"70049","area":{"x":47,"y":18,"z":38},"centroid":{"x":1591,"y":4271,"z":3183},"post":{"x":1590,"y":4268,"z":3180},"pre":{"x":1594,"y":4276,"z":3190}},{"id":"70049","area":{"x":296,"y":191,"z":552},"centroid":{"x":1607,"y":4367,"z":3424},"post":{"x":1597,"y":4345,"z":3412},"pre":{"x":1619,"y":4399,"z":3433}},{"id":"70049","area":{"x":144,"y":126,"z":168},"centroid":{"x":1613,"y":4233,"z":3300},"post":{"x":1601,"y":4220,"z":3291},"pre":{"x":1621,"y":4246,"z":3318}},{"id":"70049","area":{"x":405,"y":347,"z":339},"centroid":{"x":1649,"y":4232,"z":3345},"post":{"x":1635,"y":4214,"z":3319},"pre":{"x":1656,"y":4253,"z":3360}},{"id":"70049","area":{"x":37,"y":14,"z":27},"centroid":{"x":1645,"y":4253,"z":3370},"post":{"x":1643,"y":4248,"z":3368},"pre":{"x":1647,"y":4259,"z":3374}},{"id":"70049","area":{"x":20,"y":37,"z":6},"centroid":{"x":1656,"y":4213,"z":3307},"post":{"x":1651,"y":4211,"z":3304},"pre":{"x":1660,"y":4217,"z":3311}},{"id":"70049","area":{"x":146,"y":252,"z":240},"centroid":{"x":1668,"y":4204,"z":3418},"post":{"x":1654,"y":4192,"z":3408},"pre":{"x":1682,"y":4215,"z":3424}},{"id":"70049","area":{"x":79,"y":153,"z":132},"centroid":{"x":1687,"y":4166,"z":3357},"post":{"x":1680,"y":4158,"z":3346},"pre":{"x":1698,"y":4173,"z":3371}},{"id":"70049","area":{"x":14,"y":44,"z":13},"centroid":{"x":1693,"y":4196,"z":3222},"post":{"x":1689,"y":4195,"z":3218},"pre":{"x":1697,"y":4199,"z":3226}},{"id":"70049","area":{"x":301,"y":233,"z":432},"centroid":{"x":1715,"y":4215,"z":3212},"post":{"x":1691,"y":4203,"z":3194},"pre":{"x":1741,"y":4228,"z":3226}},{"id":"70049","area":{"x":607,"y":1807,"z":1910},"centroid":{"x":1744,"y":4205,"z":3258},"post":{"x":1697,"y":4179,"z":3234},"pre":{"x":1800,"y":4237,"z":3285}},{"id":"70049","area":{"x":0,"y":3,"z":2},"centroid":{"x":1743,"y":4202,"z":3260},"post":{"x":1743,"y":4202,"z":3260},"pre":{"x":1745,"y":4202,"z":3260}},{"id":"70049","area":{"x":67,"y":294,"z":133},"centroid":{"x":1778,"y":4187,"z":3276},"post":{"x":1753,"y":4180,"z":3263},"pre":{"x":1797,"y":4191,"z":3286}},{"id":"70049","area":{"x":1,"y":5,"z":5},"centroid":{"x":1767,"y":4203,"z":3250},"post":{"x":1766,"y":4203,"z":3250},"pre":{"x":1770,"y":4203,"z":3250}}]
